COPYING
MANIFEST.in
README
health_pediatrics_growth_charts_who_view.xml
setup.py
./__init__.py
./health_pediatrics_growth_charts_who.py
./health_pediatrics_growth_charts_who_view.xml
./tryton.cfg
./data/bmi_boys_p.xml
./data/bmi_boys_z.xml
./data/bmi_girls_p.xml
./data/bmi_girls_z.xml
./data/lhfa_boys_p.xml
./data/lhfa_boys_z.xml
./data/lhfa_girls_p.xml
./data/lhfa_girls_z.xml
./data/wfa_boys_p.xml
./data/wfa_boys_z.xml
./data/wfa_girls_p.xml
./data/wfa_girls_z.xml
./doc/index.rst
./locale/ar.po
./locale/de.po
./locale/el.po
./locale/es.po
./locale/fr.po
./locale/it_IT.po
./locale/ja_JP.po
./locale/lo.po
./locale/pt_BR.po
./locale/zh_CN.po
./report/__init__.py
./report/bmi_for_age.odt
./report/health_pediatrics_growth_charts_who_report.xml
./report/length-height_for_age.odt
./report/report_health_pediatrics_growth_charts_who.py
./report/weight_for_age.odt
./tests/__init__.py
./tests/test_health_pediatrics_growth_charts_who.py
./view/growth_charts_who_open_start_form.xml
./view/pediatrics_growth_charts_who_form.xml
./view/pediatrics_growth_charts_who_tree.xml
./wizard/__init__.py
./wizard/health_pediatrics_growth_charts_who_wizard.xml
./wizard/wizard_health_pediatrics_growth_charts_who.py
data/bmi_boys_p.xml
data/bmi_boys_z.xml
data/bmi_girls_p.xml
data/bmi_girls_z.xml
data/lhfa_boys_p.xml
data/lhfa_boys_z.xml
data/lhfa_girls_p.xml
data/lhfa_girls_z.xml
data/wfa_boys_p.xml
data/wfa_boys_z.xml
data/wfa_girls_p.xml
data/wfa_girls_z.xml
locale/ar.po
locale/de.po
locale/el.po
locale/es.po
locale/fr.po
locale/it_IT.po
locale/ja_JP.po
locale/lo.po
locale/pt_BR.po
locale/zh_CN.po
report/bmi_for_age.odt
report/health_pediatrics_growth_charts_who_report.xml
report/length-height_for_age.odt
report/weight_for_age.odt
trytond_health_pediatrics_growth_charts_who.egg-info/PKG-INFO
trytond_health_pediatrics_growth_charts_who.egg-info/SOURCES.txt
trytond_health_pediatrics_growth_charts_who.egg-info/dependency_links.txt
trytond_health_pediatrics_growth_charts_who.egg-info/entry_points.txt
trytond_health_pediatrics_growth_charts_who.egg-info/not-zip-safe
trytond_health_pediatrics_growth_charts_who.egg-info/requires.txt
trytond_health_pediatrics_growth_charts_who.egg-info/top_level.txt
view/growth_charts_who_open_start_form.xml
view/pediatrics_growth_charts_who_form.xml
view/pediatrics_growth_charts_who_tree.xml
wizard/health_pediatrics_growth_charts_who_wizard.xml